babble/Dockerfile
babble/docker_entry.py
babble/pip_entry.py
babble/providers/main.tf
babble/scripts/__init__.py
babble/scripts/classes.py
babble/scripts/functions.py
babble/scripts/preview.py
babble/templates/aws/function.py
babble/templates/aws/layer.py
babble/templates/aws/main.tf
babble_cloud-0.1.5.dist-info/WHEEL
babble_cloud-0.1.5.dist-info/entry_points.txt
babble_cloud-0.1.5.dist-info/METADATA
babble_cloud-0.1.5.dist-info/RECORD
