Metadata-Version: 2.1
Name: babble-cloud
Version: 0.1.5
Summary: Rapidly deploy serverless HTTP APIs to AWS through a low-code Pythonic YAML configuration file.
Author: mkearney2023
Author-email: mkearney2023@gmail.com
Requires-Python: >=3.0,<4.0
Classifier: Programming Language :: Python :: 3
Classifier: Programming Language :: Python :: 3.4
Classifier: Programming Language :: Python :: 3.5
Classifier: Programming Language :: Python :: 3.6
Classifier: Programming Language :: Python :: 3.7
Classifier: Programming Language :: Python :: 3.8
Classifier: Programming Language :: Python :: 3.9
Classifier: Programming Language :: Python :: 3.10
Classifier: Programming Language :: Python :: 3.11
